flat_tree/__init__.py
flat_tree/accessor.py
flat_tree/iterator.py
flat_tree-0.0.1a8.dist-info/LICENSE
flat_tree-0.0.1a8.dist-info/WHEEL
flat_tree-0.0.1a8.dist-info/METADATA
flat_tree-0.0.1a8.dist-info/RECORD
