Metadata-Version: 2.1
Name: flat-tree
Version: 0.0.1a8
Summary: Utilities for navigating flat trees
Home-page: https://github.com/hyperpy/flat-tree
Keywords: hypercore,hypercore-protocol
Author: Decentral1se
Author-email: hi@decentral1.se
Maintainer: Decentral1se
Maintainer-email: hi@decentral1.se
Requires-Python: >=3.6,<4.0
Classifier: Programming Language :: Python :: 3
Classifier: Programming Language :: Python :: 3.6
Classifier: Programming Language :: Python :: 3.7
Classifier: Programming Language :: Python :: 3.8
Requires-Dist: attrs (>=19.3.0,<20.0.0)
Project-URL: Repository, https://github.com/hyperpy/flat-tree
